kindos-0.0.1.dist-info/METADATA
kindos-0.0.1.dist-info/WHEEL
kindos-0.0.1.dist-info/licenses/LICENSE
kindos/__init__.py
kindos/build.py
kindos/colors.py
kindos/container.py
kindos/shell.py
kindos/size.py
kindos-0.0.1.dist-info/RECORD
