Metadata-Version: 2.1
Name: KindOS
Version: 0.0.1
Summary: The Developers Friendly Open Source Workspace
Author-Email: João Pinto <lamego.pinto@gmail.com>
License: MIT
Requires-Python: >=3.11
Requires-Dist: black>=23.7.0
Requires-Dist: pre-commit>=3.3.3
